python_wise_utils/__init__.py
python_wise_utils/misc_functions.py
python_wise_utils/persistent_dict.py
python_wise_utils-0.3.4.dist-info/WHEEL
python_wise_utils-0.3.4.dist-info/METADATA
python_wise_utils-0.3.4.dist-info/RECORD
