Metadata-Version: 2.1
Name: python-wise-utils
Version: 0.3.4
Summary: Python interpreter convenience utilities
Home-page: https://github.com/WisdomWolf/python_wise_utils
License: GPL-3.0-or-later
Author: Wisdom Wolf
Author-email: wisdomwolf@gmail.com
Requires-Python: >=3.6.0,<4.0.0
Classifier: License :: OSI Approved :: GNU General Public License v3 or later (GPLv3+)
Classifier: Programming Language :: Python :: 3
Classifier: Programming Language :: Python :: 3.6
Classifier: Programming Language :: Python :: 3.7
Classifier: Programming Language :: Python :: 3.8
Requires-Dist: pyyaml (>=5.3.1,<6.0.0)
Project-URL: Repository, https://github.com/WisdomWolf/python_wise_utils
